report_tool/report_tool.py
report_tool-1.1.0.dist-info/METADATA
report_tool-1.1.0.dist-info/WHEEL
report_tool-1.1.0.dist-info/top_level.txt
report_tool-1.1.0.dist-info/RECORD
