Metadata-Version: 2.1
Name: report-tool
Version: 1.1.0
Summary: Tool for Report Instagram Users
Home-page: https://github.com/Aspoky/report-tool/
Author: Aspoky
Author-email: 
License: MIT
Platform: UNKNOWN
Requires-Python: >=3.6.0
Requires-Dist: selenium (>=3.14.1)
Requires-Dist: fake-useragent (>=0.1.11)
